silence_cutter/__init__.py
silence_cutter/main.py
silencecutpy-1.2.dist-info/METADATA
silencecutpy-1.2.dist-info/WHEEL
silencecutpy-1.2.dist-info/entry_points.txt
silencecutpy-1.2.dist-info/top_level.txt
silencecutpy-1.2.dist-info/RECORD
