Metadata-Version: 2.1
Name: silencecutpy
Version: 1.2
Summary: A tool to remove silent parts from video files
Home-page: https://github.com/alameddinc/silencecut-py
Author: Alameddin Çelik
Author-email: alameddinc@gmail.com
License: UNKNOWN
Platform: UNKNOWN
Classifier: Programming Language :: Python :: 3
Classifier: Operating System :: OS Independent
Requires-Python: >=3.6
Requires-Dist: moviepy
Requires-Dist: pydub
